binfield/__init__.py
binfield/binfield.py
binfield/py.typed
BinField-0.9.3.dist-info/LICENSE
BinField-0.9.3.dist-info/METADATA
BinField-0.9.3.dist-info/WHEEL
BinField-0.9.3.dist-info/top_level.txt
BinField-0.9.3.dist-info/RECORD
