Metadata-Version: 2.1
Name: BinField
Version: 0.9.3
Summary: Python BinField implementation for binary data manipulation
Home-page: https://github.com/penguinolog/binfield
Author: Alexey Stepanov
Author-email: penguinolog@gmail.com
License: Apache License, Version 2.0
Project-URL: Bug Tracker, https://github.com/penguinolog/binfield/issues
Project-URL: Documentation, https://binfield.readthedocs.io/
Keywords: binary,binfield,development
Platform: UNKNOWN
Classifier: Development Status :: 4 - Beta
Classifier: Intended Audience :: Developers
Classifier: Topic :: Software Development :: Libraries :: Python Modules
Classifier: License :: OSI Approved :: Apache Software License
Classifier: Programming Language :: Python :: 2
Classifier: Programming Language :: Python :: 2.7
Classifier: Programming Language :: Python :: 3
Classifier: Programming Language :: Python :: 3.4
Classifier: Programming Language :: Python :: 3.5
Classifier: Programming Language :: Python :: 3.6
Classifier: Programming Language :: Python :: 3.7
Classifier: Programming Language :: Python :: Implementation :: CPython
Classifier: Programming Language :: Python :: Implementation :: PyPy
Requires-Python: >=2.7.5,!=3.0.*,!=3.1.*,!=3.2.*,!=3.3.*
Requires-Dist: six
Requires-Dist: typing (>=3.6); python_version < "3.8"
